tsapiness/__init__.py
tsapiness/connector_sav.py
tsapiness/connector_sss.py
tsapiness/connector_tsapi.py
tsapiness/tsapi.py
tsapiness-0.0.4.dist-info/LICENSE
tsapiness-0.0.4.dist-info/METADATA
tsapiness-0.0.4.dist-info/WHEEL
tsapiness-0.0.4.dist-info/top_level.txt
tsapiness-0.0.4.dist-info/RECORD
