Metadata-Version: 2.1
Name: tsapiness
Version: 0.0.4
Summary: An open source python package to connect survey data to the survey definition defined by tsapi
Author-email: Andrew Le Breuilly <andrew@arrowstream.co.uk>
License: MIT License        
Project-URL: Homepage, https://github.com/ArrowstreamUK/TSAPI-py
Project-URL: Bug Tracker, https://github.com/ArrowstreamUK/TSAPI-py/issues
Classifier: Programming Language :: Python :: 3
Classifier: License :: OSI Approved :: MIT License
Classifier: Operating System :: OS Independent
Requires-Python: >=3.9
License-File: LICENSE
Requires-Dist: requests
Requires-Dist: pyreadstat
